POMFinder/__init__.py
POMFinder/cli.py
POMFinder/main.py
POMFinder/Backend/POMFinder_443structures_100Dataset_per_Structure_xPDF_hypercube_sampling_Grmax_Name.h5
POMFinder/Backend/XGBoost_443structures_100PDFperStructure_xPDF_hypercube_sampling_Grmax.model
POMFinder/COD_ICSD_XYZs_POMs_unique99/2012944_0_0.9rscale.xyz
POMFinder/COD_ICSD_XYZs_POMs_unique99/2018792_1_0.9rscale.xyz
POMFinder/COD_ICSD_XYZs_POMs_unique99/2100052_0_1.0rscale.xyz
POMFinder/COD_ICSD_XYZs_POMs_unique99/2104477_0_0.9rscale.xyz
POMFinder/COD_ICSD_XYZs_POMs_unique99/2104477_0_1.1rscale.xyz
POMFinder/COD_ICSD_XYZs_POMs_unique99/2104634_0_1.0rscale.xyz
POMFinder/COD_ICSD_XYZs_POMs_unique99/2203989_1_0.9rscale.xyz
POMFinder/COD_ICSD_XYZs_POMs_unique99/2204268_0_0.9rscale.xyz
POMFinder/COD_ICSD_XYZs_POMs_unique99/2210056_1_0.9rscale.xyz
POMFinder/COD_ICSD_XYZs_POMs_unique99/2210842_0_1.1rscale.xyz
POMFinder/COD_ICSD_XYZs_POMs_unique99/2213065_0_1.0rscale.xyz
POMFinder/COD_ICSD_XYZs_POMs_unique99/2213065_1_0.9rscale.xyz
POMFinder/COD_ICSD_XYZs_POMs_unique99/2214383_0_0.9rscale.xyz
POMFinder/COD_ICSD_XYZs_POMs_unique99/2217558_1_0.9rscale.xyz
POMFinder/COD_ICSD_XYZs_POMs_unique99/2220478_1_0.9rscale.xyz
POMFinder/COD_ICSD_XYZs_POMs_unique99/2226169_0_1.0rscale.xyz
POMFinder/COD_ICSD_XYZs_POMs_unique99/2231207_1_0.9rscale.xyz
POMFinder/COD_ICSD_XYZs_POMs_unique99/4075110_0_0.9rscale.xyz
POMFinder/COD_ICSD_XYZs_POMs_unique99/4075111_0_0.9rscale.xyz
POMFinder/COD_ICSD_XYZs_POMs_unique99/4077982_0_1.0rscale.xyz
POMFinder/COD_ICSD_XYZs_POMs_unique99/4077983_0_0.9rscale.xyz
POMFinder/COD_ICSD_XYZs_POMs_unique99/4077983_0_1.0rscale.xyz
POMFinder/COD_ICSD_XYZs_POMs_unique99/4077984_0_0.9rscale.xyz
POMFinder/COD_ICSD_XYZs_POMs_unique99/4078020_0_1.1rscale.xyz
POMFinder/COD_ICSD_XYZs_POMs_unique99/4078139_0_1.0rscale.xyz
POMFinder/COD_ICSD_XYZs_POMs_unique99/4078271_0_1.1rscale.xyz
POMFinder/COD_ICSD_XYZs_POMs_unique99/4078273_0_1.1rscale.xyz
POMFinder/COD_ICSD_XYZs_POMs_unique99/4080389_0_1.1rscale.xyz
POMFinder-1.0.2.dist-info/LICENSE.txt
POMFinder-1.0.2.dist-info/METADATA
POMFinder-1.0.2.dist-info/WHEEL
POMFinder-1.0.2.dist-info/entry_points.txt
POMFinder-1.0.2.dist-info/top_level.txt
POMFinder-1.0.2.dist-info/RECORD
