Metadata-Version: 2.1
Name: POMFinder
Version: 1.0.2
Summary: POMFinder is a tree-based supervised learning algorithm which can predict the polyoxometalate cluster from a Pair Distribution Function.
Home-page: https://github.com/AndySAnker/POMFinder
Author: Andy S. Anker
Author-email: AndySAnker <ankerandy@gmail.com>
Project-URL: Homepage, https://github.com/AndySAnker/POMFinder
Project-URL: Bug Tracker, https://github.com/AndySAnker/POMFinder/issues
Classifier: Programming Language :: Python :: 3
Classifier: Operating System :: OS Independent
Requires-Python: >=3.7
License-File: LICENSE.txt
Requires-Dist: xgboost
Requires-Dist: numpy
Requires-Dist: matplotlib
Requires-Dist: scikit-learn
Requires-Dist: h5py
